wikinet/__init__.py
wikinet/corpus.py
wikinet/dump.py
wikinet/graph_container.py
wikinet/model.py
wikinet/net.py
wikinet/persistent_homology.py
wikinet-0.1.7.dist-info/LICENSE
wikinet-0.1.7.dist-info/METADATA
wikinet-0.1.7.dist-info/WHEEL
wikinet-0.1.7.dist-info/top_level.txt
wikinet-0.1.7.dist-info/RECORD
